LICENSE.txt
MANIFEST.in
README.md
bash_completion
setup.py
fragments/__init__.py
fragments/__main__.py
fragments/apply.py
fragments/color.py
fragments/commands.py
fragments/config.py
fragments/diff.py
fragments/precisecodevillemerge.py
fragments.egg-info/PKG-INFO
fragments.egg-info/SOURCES.txt
fragments.egg-info/dependency_links.txt
fragments.egg-info/entry_points.txt
fragments.egg-info/top_level.txt