Metadata-Version: 1.1
Name: fragments
Version: 1.2.0
Summary: tool for diff-based templating / fragmentation control
Home-page: https://github.com/glyphobet/fragments
Author: Matt Chisholm
Author-email: matt-fragments@theory.org
License: BSD License
Platform: UNKNOWN
Classifier: Development Status :: 4 - Beta
Classifier: Intended Audience :: Developers
Classifier: Natural Language :: English
Classifier: License :: OSI Approved :: BSD License
Classifier: Programming Language :: Python
Classifier: Programming Language :: Python :: 2.7
Classifier: Programming Language :: Python :: 3.2
